Workbook

Sheet Assumptions
A1: Smoothie Machine — Business Model Assumptions
A2: Blue = input | Black = calculated
A4: CAPITAL EXPENDITURE (CAPEX)
A5: HM-160E machine (landed, DHL) | B5: 4000 | C5: € — from Hommy quote 2026-03-12
A6: Sealing machine (tabletop) | B6: 250 | C6: € — manual cup sealer
A7: Mini display fridge (clear door) | B7: 350 | C7: € — holds pre-packed cups at venue
A8: Branding & signage | B8: 400 | C8: € — first location
A9: Initial setup / miscellaneous | B9: 150 | C9: € — tools, cleaning supplies
A10: TOTAL CAPEX | B10: =SUM(B5:B9)
A12: VARIABLE COSTS PER CUP
A13: Frozen fruit mix (250g @ €3.20/kg) | B13: 0.8 | C13: € — Makro Portugal, frozen blend
A14: Cup + lid (PLA, Vegware) | B14: 0.31 | C14: € — 500 units @ €0.31/unit
A15: Label / packaging print | B15: 0.05 | C15: € — custom sticker per cup
A16: Electricity per cup | B16: 0.05 | C16: € — ~0.01 kWh × €0.22/kWh × blends
A17: Cleaning supplies (amortised) | B17: 0.03 | C17: € — sanitiser, cloths
A18: TOTAL COGS per cup | B18: =SUM(B13:B17)
A20: PRICING & REVENUE SHARE
A21: Selling price per cup | B21: 4 | C21: € — target retail price
A22: Venue revenue share | B22: 0.1 | C22: % of revenue paid to venue owner
A23: Venue fee per cup (calculated) | B23: =B21*B22
A25: FIXED MONTHLY COSTS
A26: Machine depreciation (36 months) | B26: =B5/36 | C26: € — straight-line over 3 years
A27: Sealing machine depreciation (36 mo) | B27: =B6/36
A28: Regulatory / permits (annual ÷ 12) | B28: 67 | C28: € — ASAE + hygiene cert amortised
A29: Insurance | B29: 30 | C29: € — estimate
A30: TOTAL Fixed Costs / month | B30: =SUM(B26:B29)
A32: TAXES
A33: IRC corporate tax rate | B33: 0.21 | C33: % — Portugal Lda standard rate (2026)
A34: Derrama municipal surcharge | B34: 0.015 | C34: % — max 1.5%, varies by municipality
A35: Effective tax rate (IRC + derrama) | B35: =B33+B34
A36: Note: tax applies only on positive profit. Losses carry forward.
A38: Blue cells are inputs — adjust freely. All other values update automatically.

Sheet Unit Economics
A1: Unit Economics — Per Cup Sold
A3: PER-CUP WATERFALL
A4: Revenue per cup | B4: =Assumptions!B21
A5: (–) Venue fee (10%) | B5: =-Assumptions!B23
A6: (–) Frozen fruit | B6: =-Assumptions!B13
A7: (–) Cup + lid | B7: =-Assumptions!B14
A8: (–) Label | B8: =-Assumptions!B15
A9: (–) Electricity | B9: =-Assumptions!B16
A10: (–) Cleaning supplies | B10: =-Assumptions!B17
A11: CONTRIBUTION MARGIN per cup | B11: =Assumptions!B21-Assumptions!B23-Assumptions!B18
A12: Contribution margin % | B12: =B11/Assumptions!B21
A14: BREAK-EVEN ANALYSIS
A15: Fixed costs per month | B15: =Assumptions!B30
A16: Break-even cups / month | B16: =CEILING(Assumptions!B30/B11,1)
A17: Break-even cups / day (30-day month) | B17: =B16/30

Sheet Monthly Scenarios
A1: Monthly Scenarios — Cups Sold per Month
B3: 50 cups/mo | C3: 100 cups/mo | D3: 150 cups/mo | E3: 200 cups/mo | F3: 300 cups/mo | G3: 400 cups/mo
A4: Cups / month | B4: 50 | C4: 100 | D4: 150 | E4: 200 | F4: 300 | G4: 400
A5: Revenue | B5: =50*Assumptions!B21 | C5: =100*Assumptions!B21 | D5: =150*Assumptions!B21 | E5: =200*Assumptions!B21 | F5: =300*Assumptions!B21 | G5: =400*Assumptions!B21
A6: (–) Venue fee (10%) | B6: =-50*Assumptions!B23 | C6: =-100*Assumptions!B23 | D6: =-150*Assumptions!B23 | E6: =-200*Assumptions!B23 | F6: =-300*Assumptions!B23 | G6: =-400*Assumptions!B23
A7: (–) COGS (total) | B7: =-50*Assumptions!B18 | C7: =-100*Assumptions!B18 | D7: =-150*Assumptions!B18 | E7: =-200*Assumptions!B18 | F7: =-300*Assumptions!B18 | G7: =-400*Assumptions!B18
A8: Contribution margin | B8: =50*'Unit Economics'!B11 | C8: =100*'Unit Economics'!B11 | D8: =150*'Unit Economics'!B11 | E8: =200*'Unit Economics'!B11 | F8: =300*'Unit Economics'!B11 | G8: =400*'Unit Economics'!B11
A9: (–) Fixed costs | B9: =-Assumptions!B30 | C9: =-Assumptions!B30 | D9: =-Assumptions!B30 | E9: =-Assumptions!B30 | F9: =-Assumptions!B30 | G9: =-Assumptions!B30
A10: NET PROFIT before tax / month | B10: =50*'Unit Economics'!B11-Assumptions!B30 | C10: =100*'Unit Economics'!B11-Assumptions!B30 | D10: =150*'Unit Economics'!B11-Assumptions!B30 | E10: =200*'Unit Economics'!B11-Assumptions!B30 | F10: =300*'Unit Economics'!B11-Assumptions!B30 | G10: =400*'Unit Economics'!B11-Assumptions!B30
A11: (–) IRC + derrama (22.5%) | B11: =-MAX(0,50*'Unit Economics'!B11-Assumptions!B30)*Assumptions!B35 | C11: =-MAX(0,100*'Unit Economics'!B11-Assumptions!B30)*Assumptions!B35 | D11: =-MAX(0,150*'Unit Economics'!B11-Assumptions!B30)*Assumptions!B35 | E11: =-MAX(0,200*'Unit Economics'!B11-Assumptions!B30)*Assumptions!B35 | F11: =-MAX(0,300*'Unit Economics'!B11-Assumptions!B30)*Assumptions!B35 | G11: =-MAX(0,400*'Unit Economics'!B11-Assumptions!B30)*Assumptions!B35
A12: NET PROFIT after tax / month | B12: =(50*'Unit Economics'!B11-Assumptions!B30)-MAX(0,50*'Unit Economics'!B11-Assumptions!B30)*Assumptions!B35 | C12: =(100*'Unit Economics'!B11-Assumptions!B30)-MAX(0,100*'Unit Economics'!B11-Assumptions!B30)*Assumptions!B35 | D12: =(150*'Unit Economics'!B11-Assumptions!B30)-MAX(0,150*'Unit Economics'!B11-Assumptions!B30)*Assumptions!B35 | E12: =(200*'Unit Economics'!B11-Assumptions!B30)-MAX(0,200*'Unit Economics'!B11-Assumptions!B30)*Assumptions!B35 | F12: =(300*'Unit Economics'!B11-Assumptions!B30)-MAX(0,300*'Unit Economics'!B11-Assumptions!B30)*Assumptions!B35 | G12: =(400*'Unit Economics'!B11-Assumptions!B30)-MAX(0,400*'Unit Economics'!B11-Assumptions!B30)*Assumptions!B35
A13: NET PROFIT after tax / year | B13: =((50*'Unit Economics'!B11-Assumptions!B30)-MAX(0,50*'Unit Economics'!B11-Assumptions!B30)*Assumptions!B35)*12 | C13: =((100*'Unit Economics'!B11-Assumptions!B30)-MAX(0,100*'Unit Economics'!B11-Assumptions!B30)*Assumptions!B35)*12 | D13: =((150*'Unit Economics'!B11-Assumptions!B30)-MAX(0,150*'Unit Economics'!B11-Assumptions!B30)*Assumptions!B35)*12 | E13: =((200*'Unit Economics'!B11-Assumptions!B30)-MAX(0,200*'Unit Economics'!B11-Assumptions!B30)*Assumptions!B35)*12 | F13: =((300*'Unit Economics'!B11-Assumptions!B30)-MAX(0,300*'Unit Economics'!B11-Assumptions!B30)*Assumptions!B35)*12 | G13: =((400*'Unit Economics'!B11-Assumptions!B30)-MAX(0,400*'Unit Economics'!B11-Assumptions!B30)*Assumptions!B35)*12
A14: Payback — total CAPEX (months) | B14: =IF(50*'Unit Economics'!B11>Assumptions!B30,Assumptions!B10/(50*'Unit Economics'!B11-Assumptions!B30),"-") | C14: =IF(100*'Unit Economics'!B11>Assumptions!B30,Assumptions!B10/(100*'Unit Economics'!B11-Assumptions!B30),"-") | D14: =IF(150*'Unit Economics'!B11>Assumptions!B30,Assumptions!B10/(150*'Unit Economics'!B11-Assumptions!B30),"-") | E14: =IF(200*'Unit Economics'!B11>Assumptions!B30,Assumptions!B10/(200*'Unit Economics'!B11-Assumptions!B30),"-") | F14: =IF(300*'Unit Economics'!B11>Assumptions!B30,Assumptions!B10/(300*'Unit Economics'!B11-Assumptions!B30),"-") | G14: =IF(400*'Unit Economics'!B11>Assumptions!B30,Assumptions!B10/(400*'Unit Economics'!B11-Assumptions!B30),"-")
